upwork_fetcher/cli.py
upwork_fetcher/commands.py
upwork_fetcher/config.py
upwork_fetcher/models/__init__.py
upwork_fetcher/models/dbcontext/dbcontext.py
upwork_fetcher/models/jobs.py
upwork_fetcher/queries/market_place_job.py
upwork_fetcher/schema.py
upwork_fetcher/services/upwork_service.py
upwork_fetcher-0.1.16.dist-info/METADATA
upwork_fetcher-0.1.16.dist-info/WHEEL
upwork_fetcher-0.1.16.dist-info/entry_points.txt
upwork_fetcher-0.1.16.dist-info/RECORD
